get_free_port/README.md
get_free_port/__init__.py
get_free_port/requirements.txt
get_free_port/thirdparty.json
get_free_port-0.10.dist-info/LICENSE.rst
get_free_port-0.10.dist-info/METADATA
get_free_port-0.10.dist-info/WHEEL
get_free_port-0.10.dist-info/top_level.txt
get_free_port-0.10.dist-info/RECORD
