Metadata-Version: 2.1
Name: get-free-port
Version: 0.10
Summary: Get free dynamic / registered ports
Home-page: https://github.com/hansalemaos/get_free_port
Author: Johannes Fischer
Author-email: aulasparticularesdealemaosp@gmail.com
License: MIT
Keywords: port,tcp
Classifier: Development Status :: 4 - Beta
Classifier: Programming Language :: Python :: 3 :: Only
Classifier: Programming Language :: Python :: 3.10
Classifier: Topic :: Software Development :: Libraries :: Python Modules
Classifier: Topic :: Utilities
License-File: LICENSE.rst
